LICENSE
README.md
setup.py
redis_cache_deco/__init__.py
redis_cache_deco/rcd.py
redis_cache_deco.egg-info/PKG-INFO
redis_cache_deco.egg-info/SOURCES.txt
redis_cache_deco.egg-info/dependency_links.txt
redis_cache_deco.egg-info/top_level.txt