Metadata-Version: 2.1
Name: redis_cache_deco
Version: 1.0.8
Summary: A decorator that memoized into redis
Home-page: https://github.com/snuids/redis_cache_deco
Download-URL: https://github.com/snuids/redis_cache_deco/archive/1.0.8.tar.gz
Author: snuids
Author-email: snuids@mannekentech.com
Keywords: Python,memoize,decorator,redis
License-File: LICENSE
